getbestfontsize/README.MD
getbestfontsize/__init__.py
getbestfontsize/requirements.txt
getbestfontsize/thirdparty.json
getbestfontsize-0.10.dist-info/LICENSE.rst
getbestfontsize-0.10.dist-info/METADATA
getbestfontsize-0.10.dist-info/WHEEL
getbestfontsize-0.10.dist-info/top_level.txt
getbestfontsize-0.10.dist-info/RECORD
