Metadata-Version: 2.1
Name: getbestfontsize
Version: 0.10
Summary: Determines the appropriate font size for given text and constraints
Home-page: https://github.com/hansalemaos/getbestfontsize
Author: Johannes Fischer
Author-email: aulasparticularesdealemaosp@gmail.com
License: MIT
Keywords: font,size,calculate
Classifier: Development Status :: 4 - Beta
Classifier: Programming Language :: Python :: 3 :: Only
Classifier: Programming Language :: Python :: 3.10
Classifier: Topic :: Software Development :: Libraries :: Python Modules
Classifier: Topic :: Utilities
License-File: LICENSE.rst
Requires-Dist: Pillow
